dummy_url_wrapper/__init__.py
dummy_url_wrapper/mysdk.py
dummy_url_wrapper-0.0.13.dist-info/METADATA
dummy_url_wrapper-0.0.13.dist-info/WHEEL
dummy_url_wrapper-0.0.13.dist-info/top_level.txt
dummy_url_wrapper-0.0.13.dist-info/RECORD
