Metadata-Version: 2.1
Name: dummy-url-wrapper
Version: 0.0.13
Summary: This package provides the wrapping of URLs for not exposing to clients
Home-page: https://github.com/nk2909/Python-SDK.git
Author: Nishant Kabariya
Author-email: testurl@yopmail.com
Keywords: python
Classifier: Development Status :: 5 - Production/Stable
Classifier: Intended Audience :: Developers
Classifier: Operating System :: OS Independent
Requires-Dist: requests
